MANIFEST.in
README.md
setup.py
django_genericrelationview.egg-info/PKG-INFO
django_genericrelationview.egg-info/SOURCES.txt
django_genericrelationview.egg-info/dependency_links.txt
django_genericrelationview.egg-info/top_level.txt
genericrelationview/__init__.py
genericrelationview/admin.py
genericrelationview/urls.py
genericrelationview/views.py
genericrelationview/static/js/admin/generickey.js