Metadata-Version: 1.0
Name: django-genericrelationview
Version: 0.0.1
Summary: django admin interface for GenericForeignKey fields
Home-page: https://github.com/lexich/genericrelationview
Author: lexich
Author-email: lexich121@gmail.com
License: BSD
Platform: UNKNOWN
